py_heideltime/__init__.py
py_heideltime/cli.py
py_heideltime/config.py
py_heideltime/meta.py
py_heideltime/py_heideltime.py
py_heideltime/utils.py
py_heideltime/Heideltime/de.unihd.dbs.heideltime.standalone.jar
py_heideltime/Heideltime/TreeTaggerLinux/bin/separate-punctuation
py_heideltime/Heideltime/TreeTaggerLinux/bin/train-tree-tagger
py_heideltime/Heideltime/TreeTaggerLinux/bin/tree-tagger
py_heideltime/Heideltime/TreeTaggerLinux/bin/tree-tagger-flush
py_heideltime/Heideltime/TreeTaggerLinux/cmd/add-korean-sentence-markers.pl
py_heideltime/Heideltime/TreeTaggerLinux/cmd/chunker-read-lemma.perl
py_heideltime/Heideltime/TreeTaggerLinux/cmd/chunker-write-lemma.perl
py_heideltime/Heideltime/TreeTaggerLinux/cmd/filter-chunker-output-french.perl
py_heideltime/Heideltime/TreeTaggerLinux/cmd/filter-chunker-output-german.perl
py_heideltime/Heideltime/TreeTaggerLinux/cmd/filter-chunker-output.perl
py_heideltime/Heideltime/TreeTaggerLinux/cmd/filter-coordinate-output.perl
py_heideltime/Heideltime/TreeTaggerLinux/cmd/filter-german-tags
py_heideltime/Heideltime/TreeTaggerLinux/cmd/lookup.perl
py_heideltime/Heideltime/TreeTaggerLinux/cmd/mwl-lookup.perl
py_heideltime/Heideltime/TreeTaggerLinux/cmd/portuguese-splitter.perl
py_heideltime/Heideltime/TreeTaggerLinux/cmd/split-romanian.perl
py_heideltime/Heideltime/TreeTaggerLinux/cmd/tagger-chunker-english
py_heideltime/Heideltime/TreeTaggerLinux/cmd/tagger-chunker-french
py_heideltime/Heideltime/TreeTaggerLinux/cmd/tagger-chunker-german
py_heideltime/Heideltime/TreeTaggerLinux/cmd/tagger-chunker-spanish
py_heideltime/Heideltime/TreeTaggerLinux/cmd/tree-tagger-dutch
py_heideltime/Heideltime/TreeTaggerLinux/cmd/tree-tagger-english
py_heideltime/Heideltime/TreeTaggerLinux/cmd/tree-tagger-french
py_heideltime/Heideltime/TreeTaggerLinux/cmd/tree-tagger-german
py_heideltime/Heideltime/TreeTaggerLinux/cmd/tree-tagger-italian
py_heideltime/Heideltime/TreeTaggerLinux/cmd/tree-tagger-portuguese
py_heideltime-1.0.6.dist-info/LICENSE
py_heideltime-1.0.6.dist-info/METADATA
py_heideltime-1.0.6.dist-info/WHEEL
py_heideltime-1.0.6.dist-info/entry_points.txt
py_heideltime-1.0.6.dist-info/top_level.txt
py_heideltime-1.0.6.dist-info/RECORD
