Metadata-Version: 2.1
Name: py-heideltime
Version: 1.0.6
Summary: Python wrapper for HeidelTime temporal tagger.
Home-page: https://github.com/hmosousa/py_heideltime.git
Author: Jorge Mendes, Ricardo Campos, and Hugo Sousa
Author-email: hmosousa@gmail.com
License-File: LICENSE
Requires-Dist: emoji ==2.0.0
